ChangeLog
LICENSE
MANIFEST.in
README.rst
TODO
setup.py
doc/doctrees/API.doctree
doc/doctrees/README.doctree
doc/doctrees/environment.pickle
doc/doctrees/glossary.doctree
doc/doctrees/index.doctree
doc/doctrees/modules.doctree
doc/doctrees/pyptlib.doctree
doc/html/.buildinfo
doc/html/API.html
doc/html/README.html
doc/html/genindex.html
doc/html/glossary.html
doc/html/index.html
doc/html/modules.html
doc/html/objects.inv
doc/html/py-modindex.html
doc/html/pyptlib.html
doc/html/search.html
doc/html/searchindex.js
doc/html/_modules/index.html
doc/html/_modules/pyptlib/client.html
doc/html/_modules/pyptlib/client_config.html
doc/html/_modules/pyptlib/config.html
doc/html/_modules/pyptlib/server.html
doc/html/_modules/pyptlib/server_config.html
doc/html/_modules/pyptlib/util.html
doc/html/_sources/API.txt
doc/html/_sources/README.txt
doc/html/_sources/glossary.txt
doc/html/_sources/index.txt
doc/html/_sources/modules.txt
doc/html/_sources/pyptlib.txt
doc/html/_static/ajax-loader.gif
doc/html/_static/alert_info_32.png
doc/html/_static/alert_warning_32.png
doc/html/_static/basic.css
doc/html/_static/bg-page.png
doc/html/_static/bullet_orange.png
doc/html/_static/comment-bright.png
doc/html/_static/comment-close.png
doc/html/_static/comment.png
doc/html/_static/doctools.js
doc/html/_static/down-pressed.png
doc/html/_static/down.png
doc/html/_static/file.png
doc/html/_static/haiku.css
doc/html/_static/jquery.js
doc/html/_static/minus.png
doc/html/_static/plus.png
doc/html/_static/pygments.css
doc/html/_static/searchtools.js
doc/html/_static/underscore.js
doc/html/_static/up-pressed.png
doc/html/_static/up.png
doc/html/_static/websupport.js
examples/client.py
examples/server.py
pyptlib/__init__.py
pyptlib/client.py
pyptlib/client_config.py
pyptlib/config.py
pyptlib/core.py
pyptlib/server.py
pyptlib/server_config.py
pyptlib.egg-info/PKG-INFO
pyptlib.egg-info/SOURCES.txt
pyptlib.egg-info/dependency_links.txt
pyptlib.egg-info/top_level.txt
pyptlib/test/__init__.py
pyptlib/test/test_client.py
pyptlib/test/test_core.py
pyptlib/test/test_server.py
pyptlib/test/test_util.py
